kicost_digikey_api_v4/__init__.py
kicost_digikey_api_v4/exceptions.py
kicost_digikey_api_v4/utils.py
kicost_digikey_api_v4/certauth/__init__.py
kicost_digikey_api_v4/certauth/certauth.py
kicost_digikey_api_v4/oauth/__init__.py
kicost_digikey_api_v4/oauth/oauth2.py
kicost_digikey_api_v4/v4/__init__.py
kicost_digikey_api_v4/v4/api.py
kicost_digikey_api_v4/v4/productinformation/__init__.py
kicost_digikey_api_v4/v4/productinformation/api_client.py
kicost_digikey_api_v4/v4/productinformation/configuration.py
kicost_digikey_api_v4/v4/productinformation/rest.py
kicost_digikey_api_v4/v4/productinformation/api/__init__.py
kicost_digikey_api_v4/v4/productinformation/api/product_search_api.py
kicost_digikey_api_v4/v4/productinformation/models/__init__.py
kicost_digikey_api_v4/v4/productinformation/models/alternate_packaging.py
kicost_digikey_api_v4/v4/productinformation/models/alternate_packaging_response.py
kicost_digikey_api_v4/v4/productinformation/models/base_filter_v4.py
kicost_digikey_api_v4/v4/productinformation/models/base_product.py
kicost_digikey_api_v4/v4/productinformation/models/break_price.py
kicost_digikey_api_v4/v4/productinformation/models/categories_response.py
kicost_digikey_api_v4/v4/productinformation/models/category.py
kicost_digikey_api_v4/v4/productinformation/models/category_node.py
kicost_digikey_api_v4/v4/productinformation/models/category_response.py
kicost_digikey_api_v4/v4/productinformation/models/category_type.py
kicost_digikey_api_v4/v4/productinformation/models/classifications.py
kicost_digikey_api_v4/v4/productinformation/models/description.py
kicost_digikey_api_v4/v4/productinformation/models/digi_reel_pricing.py
kicost_digikey_api_v4/v4/productinformation/models/dk_problem_details.py
kicost_digikey_api_v4/v4/productinformation/models/filter_id.py
kicost_digikey_api_v4/v4/productinformation/models/filter_options.py
kicost_digikey_api_v4/v4/productinformation/models/filter_options_request.py
kicost_digikey_api_v4-0.1.3.dist-info/LICENSE
kicost_digikey_api_v4-0.1.3.dist-info/METADATA
kicost_digikey_api_v4-0.1.3.dist-info/WHEEL
kicost_digikey_api_v4-0.1.3.dist-info/top_level.txt
kicost_digikey_api_v4-0.1.3.dist-info/RECORD
